{
  "receivers": [
    {
      "uid": "16600621186956491044",
      "name": "PiPicoW",
      "type": "PiPicoW",
      "householdID": -1,
      "gpio": [
        {
          "value": 1,
          "index": 0,
          "uid": "16600621186956491044"
        },
        {
          "value": 0,
          "index": 1,
          "uid": "16600621186956491044"
        },
        {
          "value": 0,
          "index": 2,
          "uid": "16600621186956491044"
        },
        {
          "value": 0,
          "index": 3,
          "uid": "16600621186956491044"
        },
        {
          "value": 0,
          "index": 4,
          "uid": "16600621186956491044"
        },
        {
          "value": -1,
          "index": 5,
          "uid": "16600621186956491044",
          "sensor": {
            "receiverID": "",
            "index": 5,
            "name": "DHT11",
            "className": "DHT11",
            "numValues": 2,
            "valueNames": [
              "Humidity",
              "Temperature"
            ],
            "values": []
          }
        },
        {
          "value": 0,
          "index": 6,
          "uid": "16600621186956491044"
        },
        {
          "value": 0,
          "index": 7,
          "uid": "16600621186956491044"
        },
        {
          "value": 0,
          "index": 8,
          "uid": "16600621186956491044"
        },
        {
          "value": 0,
          "index": 9,
          "uid": "16600621186956491044"
        },
        {
          "value": 0,
          "index": 10,
          "uid": "16600621186956491044"
        },
        {
          "value": 0,
          "index": 11,
          "uid": "16600621186956491044"
        },
        {
          "value": 0,
          "index": 12,
          "uid": "16600621186956491044"
        },
        {
          "value": 0,
          "index": 13,
          "uid": "16600621186956491044"
        },
        {
          "value": 0,
          "index": 14,
          "uid": "16600621186956491044"
        },
        {
          "value": 0,
          "index": 15,
          "uid": "16600621186956491044"
        },
        {
          "value": 0,
          "index": 16,
          "uid": "16600621186956491044"
        },
        {
          "value": 0,
          "index": 17,
          "uid": "16600621186956491044"
        },
        {
          "value": 0,
          "index": 18,
          "uid": "16600621186956491044"
        },
        {
          "value": 0,
          "index": 19,
          "uid": "16600621186956491044"
        },
        {
          "value": 0,
          "index": 20,
          "uid": "16600621186956491044"
        },
        {
          "value": 0,
          "index": 21,
          "uid": "16600621186956491044"
        },
        {
          "value": 0,
          "index": 22,
          "uid": "16600621186956491044"
        }
      ],
      "sensors": [
        null,
        null,
        null
      ],
      "connected": true
    }
  ]
}